mtai/__init__.py
mtai/base.py
mtai/bios.py
mtai/descriptions.py
mtai/mt.py
mtai/prompts.py
mtai/tags.py
mtai/transcribes.py
mtai-0.1.0.dist-info/LICENSE
mtai-0.1.0.dist-info/METADATA
mtai-0.1.0.dist-info/WHEEL
mtai-0.1.0.dist-info/top_level.txt
mtai-0.1.0.dist-info/RECORD
