Metadata-Version: 2.1
Name: mtai
Version: 0.1.0
Summary: A python library to consume meditranscribe ai API
Home-page: https://github.com/mediatranscribe/mt-ai-python
Author: KtechHub
Author-email: pypi@ktechhub.com
License: MIT
Keywords: mtai mediatranscribe mtaiapi python library
Classifier: Intended Audience :: Developers
Classifier: License :: OSI Approved :: MIT License
Classifier: Programming Language :: Python :: 3
Classifier: Programming Language :: Python :: 3.8
Classifier: Programming Language :: Python :: 3.9
Classifier: Programming Language :: Python :: 3.10
Requires-Python: >=3.8.0
License-File: LICENSE
Requires-Dist: requests
Provides-Extra: test
Requires-Dist: coverage ; extra == 'test'
